hostinit/__init__.py
hostinit/bundlemgr.py
hostinit/bundles.py
hostinit/certificates.py
hostinit/cli.py
hostinit/command.py
hostinit/constants.py
hostinit/ebsnvme.py
hostinit/exception.py
hostinit/hostinfo.py
hostinit/httpsessionmgr.py
hostinit/network.py
hostinit/osfamily.py
hostinit/osinfo.py
hostinit/rest.py
hostinit/retry.py
hostinit/storage.py
hostinit/storagemgr.py
hostinit/util.py
hostinit/data/config/disable-thp
hostinit/data/config/packages.json
hostinit/data/config/tuned.conf
hostinit/data/playbooks/aws_cli.yaml
hostinit/data/playbooks/az_cli_apt.yaml
hostinit/data/playbooks/az_cli_dnf.yaml
hostinit/data/playbooks/base_sw_amzn.yaml
hostinit/data/playbooks/base_sw_apt.yaml
hostinit/data/playbooks/base_sw_yum.yaml
hostinit/data/playbooks/base_sw_zypper.yaml
hostinit/data/playbooks/configure_data_mnt.yaml
hostinit/data/playbooks/configure_swap.yaml
hostinit/data/playbooks/configure_swappiness.yaml
hostinit/data/playbooks/disable_dns_stub.yaml
hostinit/data/playbooks/disable_firewall_dep.yaml
hostinit/data/playbooks/disable_firewalld_rhel.yaml
hostinit/data/playbooks/disable_thp_amzn.yaml
hostinit/data/playbooks/disable_thp_deb.yaml
hostinit/data/playbooks/disable_thp_rhel.yaml
hostinit/data/playbooks/disable_thp_sles.yaml
hostinit/data/playbooks/enable_chrony_dep.yaml
hostinit/data/playbooks/enable_chrony_rhel.yaml
hostinit/data/playbooks/gcp_cli_apt.yaml
hostinit/data/playbooks/gcp_cli_dnf.yaml
hostinit/data/playbooks/mem_tune.yaml
hostinit-1.0.2.dist-info/METADATA
hostinit-1.0.2.dist-info/WHEEL
hostinit-1.0.2.dist-info/entry_points.txt
hostinit-1.0.2.dist-info/licenses/LICENSE.txt
hostinit-1.0.2.dist-info/RECORD
