Metadata-Version: 2.4
Name: hostinit
Version: 1.0.2
Summary: Host Configuration Automation
Project-URL: Homepage, https://github.com/mminichino/hostinit
Author-email: Michael Minichino <info@unix.us.com>
License-File: LICENSE.txt
Keywords: automation,devops
Classifier: Development Status :: 5 - Production/Stable
Classifier: Intended Audience :: Developers
Classifier: License :: OSI Approved :: MIT License
Classifier: Operating System :: OS Independent
Classifier: Programming Language :: Python
Classifier: Programming Language :: Python :: 3
Classifier: Topic :: Database
Classifier: Topic :: Software Development :: Libraries
Classifier: Topic :: Software Development :: Libraries :: Python Modules
Requires-Python: <4,>=3.9
Requires-Dist: ansible-runner>=2.3.3
Requires-Dist: ansible>=6.7.0
Requires-Dist: attrs>=21.2.0
Requires-Dist: docker>=5.0.3
Requires-Dist: jinja2>=3.0.0
Requires-Dist: overrides>=7.4.0
Requires-Dist: psutil>=5.9.5
Requires-Dist: requests>=2.25.1
Requires-Dist: urllib3>=1.26.5
Provides-Extra: dev
Requires-Dist: hatch; extra == 'dev'
Provides-Extra: test
Requires-Dist: pytest-asyncio>=0.23.6; extra == 'test'
Requires-Dist: pytest-mock>=3.6.1; extra == 'test'
Requires-Dist: pytest-rerunfailures>=10.3; extra == 'test'
Requires-Dist: pytest>=8.1.1; extra == 'test'
